make_box/__init__.py
make_box-0.0.4.dist-info/METADATA
make_box-0.0.4.dist-info/WHEEL
make_box-0.0.4.dist-info/top_level.txt
make_box-0.0.4.dist-info/RECORD
