Metadata-Version: 2.1
Name: make-box
Version: 0.0.4
Keywords: python,sockets
Classifier: Development Status :: 1 - Planning
Requires-Dist: pycryptodome
Requires-Dist: discord-webhook
